cclogs/__init__.py
cclogs/extras.py
cclogs/formatter.py
cclogs/handler.py
cclogs/utils.py
cclogs-1.0.4.dist-info/LICENSE
cclogs-1.0.4.dist-info/METADATA
cclogs-1.0.4.dist-info/WHEEL
cclogs-1.0.4.dist-info/top_level.txt
cclogs-1.0.4.dist-info/RECORD
