Metadata-Version: 2.1
Name: cclogs
Version: 1.0.4
Summary: Colored console logs
Home-page: https://github.com/tom4c-hunify/colored-console-log
Author: Peter Tomek
Author-email: tomek@hunifylabs.com
License: UNKNOWN
Platform: UNKNOWN
Classifier: Programming Language :: Python :: 3
Classifier: License :: OSI Approved :: MIT License
Classifier: Operating System :: OS Independent
Requires-Python: >=3.6
